domainfinder0101/__init__.py
domainfinder0101/a.py
domainfinder0101/o.py
domainfinder0101/trial.py
domainfinder0101/dnsdumpster/API_example.py
domainfinder0101/dnsdumpster/DNSDumpsterAPI.py
domainfinder0101/dnsdumpster/__init__.py
domainfinder0101/dnsdumpster/test_api.py
domainfinder010101-0.0.4.dist-info/LICENSE
domainfinder010101-0.0.4.dist-info/METADATA
domainfinder010101-0.0.4.dist-info/WHEEL
domainfinder010101-0.0.4.dist-info/top_level.txt
domainfinder010101-0.0.4.dist-info/RECORD
