Metadata-Version: 2.1
Name: domainfinder010101
Version: 0.0.4
Author: rohit
Author-email: rk0901308@gmail.com
License: MIT
Classifier: Programming Language :: Python :: 3
Classifier: License :: OSI Approved :: MIT License
Classifier: Operating System :: OS Independent
License-File: LICENSE
Requires-Dist: numpy
Requires-Dist: pandas
Requires-Dist: requests
Requires-Dist: pathlib
Requires-Dist: bs4
Requires-Dist: regex
Requires-Dist: future
